Elastic_logger-1.0.7.dist-info/METADATA
Elastic_logger-1.0.7.dist-info/RECORD
Elastic_logger-1.0.7.dist-info/WHEEL
Elastic_logger-1.0.7.dist-info/top_level.txt
elasticlogger/__init__.py
elasticlogger/elastic.py
elasticlogger/logger.py
