Metadata-Version: 2.1
Name: Elastic-logger
Version: 1.0.7
Summary: Solution created for segregation of logs for the elasticsearch in python
Home-page: https://github.com/silva-willian/elastic-logger
Author: Willian da Silva
Author-email: silva.willian@outlook.com
License: Apache2
Platform: UNKNOWN
Classifier: Development Status :: 4 - Beta
Classifier: Intended Audience :: System Administrators
Classifier: License :: OSI Approved :: Apache Software License
Classifier: Programming Language :: Python :: 2.7
Classifier: Programming Language :: Python :: 3
Requires-Dist: python-dotenv (==0.8.2)
Requires-Dist: jsonpickle (==0.9.6)
Requires-Dist: elasticsearch (==6.2.0)
